{
  "/_not-found": 105472,
  "/api/auth/microsoft": 104448,
  "/api/auth/microsoft/callback": 104448,
  "/api/dev/metrics": 104448,
  "/api/dev/metrics/clear": 104448,
  "/auth/callback": 104448,
  "/bases": 114688,
  "/bases/[id]/importar": 182272,
  "/composicoes": 114688,
  "/composicoes/[id]": 109568,
  "/composicoes/[id]/editar": 177152,
  "/composicoes/importar": 181248,
  "/composicoes/nova": 176128,
  "/dashboard": 108544,
  "/dev/performance": 105472,
  "/insumos": 180224,
  "/insumos/[id]/editar": 176128,
  "/insumos/[id]/historico": 104448,
  "/insumos/importar": 180224,
  "/insumos/importar/cotacao": 180224,
  "/insumos/importar/sinapi": 181248,
  "/insumos/novo": 175104,
  "/login": 180224,
  "/logs": 176128,
  "/orcamentos": 177152,
  "/orcamentos/[id]": 107520,
  "/orcamentos/[id]/caderno": 106496,
  "/orcamentos/[id]/composicoes": 178176,
  "/orcamentos/[id]/composicoes/[compId]": 178176,
  "/orcamentos/[id]/configuracoes": 110592,
  "/orcamentos/[id]/curva-abc": 115712,
  "/orcamentos/[id]/editar": 175104,
  "/orcamentos/[id]/importar": 178176,
  "/orcamentos/[id]/insumos": 179200,
  "/orcamentos/[id]/logs": 112640,
  "/orcamentos/[id]/planilha": 217088,
  "/orcamentos/[id]/relatorios": 119808,
  "/orcamentos/[id]/versoes": 112640,
  "/orcamentos/novo": 176128,
  "/projetos": 172032,
  "/signup": 174080
}
